setup.py
ctree/__init__.py
ctree/analyses.py
ctree/codegen.py
ctree/defaults.cfg
ctree/dotgen.py
ctree/frontend.py
ctree/jit.py
ctree/nodes.py
ctree/precedence.py
ctree/transformations.py
ctree/tune.py
ctree/types.py
ctree/util.py
ctree/visitors.py
ctree.egg-info/PKG-INFO
ctree.egg-info/SOURCES.txt
ctree.egg-info/dependency_links.txt
ctree.egg-info/entry_points.txt
ctree.egg-info/requires.txt
ctree.egg-info/top_level.txt
ctree/c/__init__.py
ctree/c/codegen.py
ctree/c/dotgen.py
ctree/c/macros.py
ctree/c/nodes.py
ctree/cilk/__init__.py
ctree/cilk/codegen.py
ctree/cilk/dotgen.py
ctree/cilk/nodes.py
ctree/cpp/__init__.py
ctree/cpp/codegen.py
ctree/cpp/dotgen.py
ctree/cpp/nodes.py
ctree/metrics/__init__.py
ctree/metrics/watts_up_reader.py
ctree/np/__init__.py
ctree/ocl/__init__.py
ctree/ocl/codegen.py
ctree/ocl/dotgen.py
ctree/ocl/macros.py
ctree/ocl/nodes.py
ctree/ocl/types.py
ctree/omp/__init__.py
ctree/omp/codegen.py
ctree/omp/dotgen.py
ctree/omp/macros.py
ctree/omp/nodes.py
ctree/opentuner/__init__.py
ctree/opentuner/driver.py
ctree/py/__init__.py
ctree/py/dotgen.py
ctree/simd/__init__.py
ctree/simd/codegen.py
ctree/simd/dotgen.py
ctree/simd/macros.py
ctree/simd/nodes.py
ctree/simd/types.py
ctree/templates/__init__.py
ctree/templates/codegen.py
ctree/templates/dotgen.py
ctree/templates/nodes.py
ctree/tools/__init__.py
ctree/tools/runner.py
ctree/tools/generators/__init__.py
ctree/tools/generators/builder.py
ctree/tools/generators/templates/__init__.py
ctree/transforms/__init__.py
ctree/transforms/constant_fold.py
ctree/transforms/declaration_filler.py
ctree/visual/__init__.py
ctree/visual/dot_manager.py
test/test_ArrayDefs.py
test/test_analyses.py
test/test_assign.py
test/test_augassign.py
test/test_binops.py
test/test_c_macros.py
test/test_call.py
test/test_casts.py
test/test_constants.py
test/test_control.py
test/test_cpp.py
test/test_ctree_nodes.py
test/test_decls.py
test/test_dot.py
test/test_dot_manager.py
test/test_examples.py
test/test_file.py
test/test_flattening.py
test/test_frontend.py
test/test_funcdecls.py
test/test_highlight.py
test/test_import.py
test/test_jit.py
test/test_lambda.py
test/test_lifter.py
test/test_numpy.py
