Metadata-Version: 1.0
Name: ctree
Version: 0.1.9
Summary: A C-family AST implementation designed to be an IR for DSL compilers.
Home-page: UNKNOWN
Author: UNKNOWN
Author-email: UNKNOWN
License: UNKNOWN
Platform: UNKNOWN
